unscrambler_words/__init__.py
unscrambler_words/unscrambler_words.py
unscrambler_words-1.0.0.dist-info/METADATA
unscrambler_words-1.0.0.dist-info/WHEEL
unscrambler_words-1.0.0.dist-info/entry_points.txt
unscrambler_words-1.0.0.dist-info/top_level.txt
unscrambler_words-1.0.0.dist-info/RECORD
