Metadata-Version: 2.4
Name: unscrambler_words
Version: 1.0.0
Summary: A simple word unscrambler using permutations
Author-email: Faisal <faisal@nihongoproject.com>
Keywords: word unscrambler,permutations,word games
Classifier: License :: OSI Approved :: The Unlicense (Unlicense)
Classifier: Programming Language :: Python :: 3
Classifier: Operating System :: OS Independent
Requires-Python: >=3.7
Requires-Dist: pandas>=2.3.0
